Metadata-Version: 1.0
Name: udacity-probability-prac
Version: 1.0
Summary: Gaussian and Binomial distributions
Home-page: UNKNOWN
Author: Chan Liang
Author-email: mitbbskg@gmail.com
License: UNKNOWN
Platform: UNKNOWN
